Metadata-Version: 2.1
Name: cgai-excel
Version: 0.0.6
Summary: An Excel processing tool.
Home-page: https://github.com/zxzxde/cgai-excel
Author: Master Zhang
Author-email: 360014296@qq.com
License: UNKNOWN
Platform: UNKNOWN
Classifier: License :: OSI Approved :: GNU General Public License v3 (GPLv3)
Classifier: Operating System :: OS Independent
Classifier: Programming Language :: Python :: 3
Classifier: Programming Language :: Python :: 3.5
Classifier: Programming Language :: Python :: 3.6
Classifier: Programming Language :: Python :: 3.7
Classifier: Programming Language :: Python :: 3.8
Classifier: Programming Language :: Python :: 3.9
